django_markdowns/__init__.py
django_markdowns/apps.py
django_markdowns/extensions.py
django_markdowns/settings.py
django_markdowns/tests.py
django_markdowns/templatetags/__init__.py
django_markdowns/templatetags/markdowns.py
django_markdowns-0.5.3.dist-info/licenses/LICENSE
django_markdowns-0.5.3.dist-info/METADATA
django_markdowns-0.5.3.dist-info/WHEEL
django_markdowns-0.5.3.dist-info/top_level.txt
django_markdowns-0.5.3.dist-info/RECORD
