Metadata-Version: 2.4
Name: django_markdowns
Version: 0.5.3
Summary: Bring markdown functionality to Django.
Author-email: "J. Nathanael Philipp" <nathanael@philipp.land>
License-Expression: GPL-3.0-or-later
Project-URL: Homepage, http://github.com/jnphilipp/django-markdowns
Project-URL: Bug Tracker, http://github.com/jnphilipp/django-markdowns/issues
Keywords: django,markdown
Classifier: Development Status :: 5 - Production/Stable
Classifier: Environment :: Web Environment
Classifier: Intended Audience :: Developers
Classifier: Operating System :: OS Independent
Classifier: Framework :: Django
Classifier: Framework :: Django :: 4.2
Classifier: Framework :: Django :: 5.1
Classifier: Framework :: Django :: 5.2
Classifier: Programming Language :: Python
Classifier: Programming Language :: Python :: 3.10
Classifier: Programming Language :: Python :: 3.11
Classifier: Programming Language :: Python :: 3.12
Classifier: Programming Language :: Python :: 3.13
Classifier: Topic :: Software Development :: Libraries :: Python Modules
Requires-Python: >=3.10
License-File: LICENSE
Requires-Dist: markdown~=3.6.0
Requires-Dist: django>=3.2.0
Dynamic: license-file
